pyquet/__init__.py
pyquet/pyquet_generator.py
pyquet/modules/__init__.py
pyquet/modules/common.py
pyquet/modules/editor.py
pyquet/modules/editor_ui.py
pyquet/modules/generator.py
pyquet/modules/schemas.py
pyquet-1.0.7.dist-info/licenses/LICENSE
pyquet-1.0.7.dist-info/METADATA
pyquet-1.0.7.dist-info/WHEEL
pyquet-1.0.7.dist-info/entry_points.txt
pyquet-1.0.7.dist-info/top_level.txt
pyquet-1.0.7.dist-info/RECORD
